Metadata-Version: 2.1
Name: lightmysql
Version: 1.1.9
Summary: The improved-package of pymysql.
Home-page: https://github.com/Danny-Yxzl/lightmysql
Author: Yixiangzhilv
Author-email: mail@yixiangzhilv.com
Project-URL: Bug Reports, https://github.com/Danny-Yxzl/lightmysql/issues
Project-URL: Say Thanks!, https://www.yixiangzhilv.com/
Project-URL: Source, https://github.com/Danny-Yxzl/lightmysql
Keywords: sql mysql pymysql database
Classifier: Intended Audience :: Developers
Classifier: License :: OSI Approved :: MIT License
Classifier: Programming Language :: Python :: 3
Classifier: Programming Language :: Python :: 3.6
Classifier: Programming Language :: Python :: 3.7
Classifier: Programming Language :: Python :: 3.8
Classifier: Programming Language :: Python :: 3.9
Classifier: Programming Language :: Python :: 3.10
License-File: LICENSE.txt
